data_loaders/__init__.py
data_loaders/azure_data_loader.py
data_loaders/file_data_loader.py
data_loaders/hive_data_loader.py
data_loaders/sql_server_data_loader.py
data_providers/__init__.py
data_providers/data_provider.py
derivation_method/__init__.py
derivation_method/action.py
derivation_method/derivation_method.py
derivation_method/method.py
derivation_method/predict_links.cql
derivation_method/predict_output_classes.cql
derivation_method/super_method.py
derivation_method/utils.py
logger/__init__.py
logger/logger.py
model_appliers/__init__.py
model_appliers/model_applier.py
model_managers/__init__.py
model_managers/model_manager.py
query_builders/__init__.py
query_builders/query_builder.py
tab2neo-2.0.3.0.dist-info/LICENSE
tab2neo-2.0.3.0.dist-info/METADATA
tab2neo-2.0.3.0.dist-info/WHEEL
tab2neo-2.0.3.0.dist-info/top_level.txt
tab2neo-2.0.3.0.dist-info/RECORD
