Metadata-Version: 2.1
Name: tab2neo
Version: 2.0.3.0
Summary: Clinical Linked Data: High-level Python classes to load, model and reshape tabular data imported into Neo4j database
Home-page: UNKNOWN
Author: Alexey Kuznetsov
License: Apache License
Requires-Dist: azure-core (==1.26.1)
Requires-Dist: azure-identity (==1.6.0)
Requires-Dist: azure-storage-blob (==12.14.1)
Requires-Dist: azure-storage-file-datalake (==12.4.0)
Requires-Dist: cffi (==1.15.1)
Requires-Dist: colorlog (==6.6.0)
Requires-Dist: cryptography (==38.0.3)
Requires-Dist: datacompy (==0.7.2)
Requires-Dist: Deprecated (==1.2.13)
Requires-Dist: et-xmlfile (==1.1.0)
Requires-Dist: isodate (==0.6.1)
Requires-Dist: JayDeBeApi (==1.2.3)
Requires-Dist: JPype1 (==1.4.1)
Requires-Dist: msal (==1.20.0)
Requires-Dist: msal-extensions (==0.3.1)
Requires-Dist: msrest (==0.7.1)
Requires-Dist: neointerface (==4.1.2)
Requires-Dist: oauthlib (==3.2.2)
Requires-Dist: openpyxl (==3.0.7)
Requires-Dist: portalocker (==2.6.0)
Requires-Dist: pyarrow (==12.0.1)
Requires-Dist: pycparser (==2.21)
Requires-Dist: PyGithub (==1.55)
Requires-Dist: PyJWT (==2.6.0)
Requires-Dist: PyNaCl (==1.5.0)
Requires-Dist: pyreadr (==0.4.0)
Requires-Dist: pyreadstat (==1.0.8)
Requires-Dist: requests-oauthlib (==1.3.1)
Requires-Dist: typing-extensions (==4.4.0)
Requires-Dist: wrapt (==1.14.1)
Requires-Dist: xlrd (==2.0.1)
